ertis_auth_migrate-0.1.6.data/scripts/ertis_auth_migrate
src/__init__.py
ertis_auth_migrate-0.1.6.dist-info/LICENSE
ertis_auth_migrate-0.1.6.dist-info/METADATA
ertis_auth_migrate-0.1.6.dist-info/WHEEL
ertis_auth_migrate-0.1.6.dist-info/top_level.txt
ertis_auth_migrate-0.1.6.dist-info/RECORD
