Metadata-Version: 2.1
Name: ertis-auth-migrate
Version: 0.1.6
Summary: Ertis Auth initializer CLI
Home-page: https://github.com/ismetacar/ertis_auth_cli
Author: ismetacar
Author-email: dismetacar@gmail.com
License: UNKNOWN
Platform: UNKNOWN
Classifier: Programming Language :: Python :: 3
Classifier: License :: OSI Approved :: MIT License
Classifier: Operating System :: OS Independent
Requires-Dist: click (~=7.1.2)
Requires-Dist: pymongo (~=3.11.2)
Requires-Dist: passlib (~=1.7.4)
Requires-Dist: setuptools (~=51.1.2)
Requires-Dist: PyInquirer (~=1.0.3)
Requires-Dist: python-slugify (==4.0.1)
Requires-Dist: bcrypt (==3.2.0)
Requires-Dist: dnspython (==1.16.0)
